{
  "fecha_analisis": "2025-07-19T22:19:56.187420",
  "repositorio_padre": {
    "existe": true,
    "componentes_encontrados": [
      {
        "nombre": "Context-Engineering-Intro",
        "existe": true,
        "tipo": "directorio",
        "readme_existe": true
      },
      {
        "nombre": "PRPs-agentic-eng",
        "existe": true,
        "tipo": "directorio",
        "readme_existe": true
      },
      {
        "nombre": "SuperClaude_Framework-master",
        "existe": true,
        "tipo": "directorio",
        "readme_existe": true
      },
      {
        "nombre": "prp-framework-esp",
        "existe": true,
        "tipo": "directorio",
        "readme_existe": true
      }
    ],
    "documentacion_principal": []
  },
  "sistema_traduccion": {
    "existe": true,
    "repositorios_traducidos": [
      {
        "nombre": "superclaude-framework-esp",
        "archivos_traducidos": 0,
        "readme_traducido": false
      },
      {
        "nombre": "servidor-mcp-esp",
        "archivos_traducidos": 7,
        "readme_traducido": true
      },
      {
        "nombre": "context-engineering-intro-esp",
        "archivos_traducidos": 4,
        "readme_traducido": true
      },
      {
        "nombre": "prps-agentic-eng-esp",
        "archivos_traducidos": 3,
        "readme_traducido": true
      }
    ],
    "herramientas_operativas": [],
    "comandos_disponibles": [
      "actualizar_repo_github",
      "revisar-traduccion",
      "generar-reporte",
      "traducir-archivo-execute",
      "traducir-repo-execute",
      "traducir-archivo-create",
      "traducir-repo-create",
      "status-traduccion",
      "validar-terminologia"
    ]
  },
  "gaps_identificados": [],
  "oportunidades_mejora": [
    "Sistema de traducción robusto (3 frameworks activos) listo para automatización",
    "Sistema de comandos completo (9 comandos) operativo"
  ],
  "prioridades_actualizacion": [
    {
      "nivel": "ALTA",
      "area": "Servidor MCP",
      "accion": "Completar traducción de archivos de código fuente restantes",
      "impacto": "Primera referencia MCP completa en español"
    },
    {
      "nivel": "MEDIA",
      "area": "Sincronización",
      "accion": "Implementar detección automática de cambios en repositorios padre",
      "impacto": "Mantener traducciones actualizadas automáticamente"
    }
  ]
}